text_db/__init__.py
text_db/converter.py
text_db/text_db.py
TextDB_lunfman-0.0.7.dist-info/LICENSE
TextDB_lunfman-0.0.7.dist-info/METADATA
TextDB_lunfman-0.0.7.dist-info/WHEEL
TextDB_lunfman-0.0.7.dist-info/top_level.txt
TextDB_lunfman-0.0.7.dist-info/RECORD
