Metadata-Version: 2.1
Name: TextDB-lunfman
Version: 0.0.7
Summary: package for creating simple text based db
Home-page: https://github.com/lunfman/TextDb
Author: lunfman
Project-URL: Bug Tracker, https://github.com/lunfman/TextDb/issues
Classifier: Programming Language :: Python :: 3
Classifier: License :: OSI Approved :: MIT License
Classifier: Operating System :: OS Independent
Requires-Python: >=3.6
License-File: LICENSE
